pyshtools/_SHTOOLS.cp312-win_amd64.pyd
pyshtools/__init__.py
pyshtools/backends/backends.py
pyshtools/backends/ducc0_wrapper.py
pyshtools/backends/shtools.py
pyshtools/backends/__init__.py
pyshtools/constants/Callisto.py
pyshtools/constants/Ceres.py
pyshtools/constants/Earth.py
pyshtools/constants/Enceladus.py
pyshtools/constants/Eros.py
pyshtools/constants/Europa.py
pyshtools/constants/Ganymede.py
pyshtools/constants/Io.py
pyshtools/constants/Mars.py
pyshtools/constants/Mercury.py
pyshtools/constants/Moon.py
pyshtools/constants/Titan.py
pyshtools/constants/Venus.py
pyshtools/constants/Vesta.py
pyshtools/constants/__init__.py
pyshtools/datasets/Callisto.py
pyshtools/datasets/Ceres.py
pyshtools/datasets/Enceladus.py
pyshtools/datasets/Eros.py
pyshtools/datasets/Europa.py
pyshtools/datasets/Ganymede.py
pyshtools/datasets/Io.py
pyshtools/datasets/Mercury.py
pyshtools/datasets/Titan.py
pyshtools/datasets/Vesta.py
pyshtools/datasets/__init__.py
pyshtools/datasets/Earth/__init__.py
pyshtools/datasets/Earth/Earth2012/__init__.py
pyshtools/datasets/Earth/Earth2014/__init__.py
pyshtools/datasets/Mars/__init__.py
pyshtools/datasets/Mars/historical/gravity.py
pyshtools/datasets/Mars/historical/magnetic.py
pyshtools/datasets/Mars/historical/shape.py
pyshtools/datasets/Mars/historical/__init__.py
pyshtools/datasets/Moon/__init__.py
pyshtools/datasets/Moon/historical/gravity.py
pyshtools/datasets/Moon/historical/shape.py
pyshtools/datasets/Moon/historical/__init__.py
pyshtools/datasets/Venus/__init__.py
pyshtools/datasets/Venus/historical/shape.py
pyshtools/datasets/Venus/historical/__init__.py
pyshtools/doc/batohilmdh.doc
pyshtools/doc/batohilmrhohdh.doc
pyshtools/doc/cilmminusdh.doc
pyshtools/doc/cilmminusrhohdh.doc
pyshtools/doc/cilmplusdh.doc
pyshtools/doc/cilmplusrhohdh.doc
pyshtools/doc/computedg82.doc
pyshtools/doc/computedm.doc
pyshtools/doc/computedmap.doc
pyshtools/doc/curve2mask.doc
pyshtools/doc/dhaj.doc
pyshtools/doc/djpi2.doc
pyshtools/doc/downcontfilterma.doc
pyshtools_winmac-4.12.2.dist-info/DELVEWHEEL
pyshtools_winmac-4.12.2.dist-info/METADATA
pyshtools_winmac-4.12.2.dist-info/RECORD
pyshtools_winmac-4.12.2.dist-info/WHEEL
